simple_sign/__init__.py
simple_sign/sign.py
tencentcloud_simple_sign-1.0.1.dist-info/LICENSE
tencentcloud_simple_sign-1.0.1.dist-info/METADATA
tencentcloud_simple_sign-1.0.1.dist-info/WHEEL
tencentcloud_simple_sign-1.0.1.dist-info/top_level.txt
tencentcloud_simple_sign-1.0.1.dist-info/RECORD
